tiingo_fetcher/__init__.py
tiingo_fetcher/fetch_data.py
tiingo_fetcher-0.1.1.dist-info/METADATA
tiingo_fetcher-0.1.1.dist-info/WHEEL
tiingo_fetcher-0.1.1.dist-info/top_level.txt
tiingo_fetcher-0.1.1.dist-info/RECORD
