Metadata-Version: 2.2
Name: tiingo_fetcher
Version: 0.1.1
Summary: Fetch large amounts of historical stock data from Tiingo for free.
Home-page: https://github.com/chaikrk/tiingo-data-fetcher
Author: Abdulmalik ALossimi
Author-email: abdulmalikosaimy@gmail.com
Classifier: Programming Language :: Python :: 3
Classifier: Operating System :: OS Independent
Requires-Python: >=3.7
Requires-Dist: pandas
Requires-Dist: requests
Requires-Dist: python-dateutil
Requires-Dist: python-dotenv
Dynamic: author
Dynamic: author-email
Dynamic: classifier
Dynamic: description
Dynamic: description-content-type
Dynamic: home-page
Dynamic: requires-dist
Dynamic: requires-python
Dynamic: summary
